prometheus_kubernetes_cli/__init__.py
prometheus_kubernetes_cli/auth.py
prometheus_kubernetes_cli/connect/aws_connect.py
prometheus_kubernetes_cli/connect/custom_connect.py
prometheus_kubernetes_cli/custom_connect.py
prometheus_kubernetes_cli/exceptions.py
prometheus_kubernetes_cli/models.py
prometheus_kubernetes_cli/utils.py
prometheus_kubernetes_cli-0.1.3.dist-info/METADATA
prometheus_kubernetes_cli-0.1.3.dist-info/WHEEL
prometheus_kubernetes_cli-0.1.3.dist-info/RECORD
