Metadata-Version: 2.1
Name: prometheus-kubernetes-cli
Version: 0.1.3
Summary: 
Author: Avi Kotlicky
Author-email: kotlickya@gmail.com
Requires-Python: >=3.8,<4.0
Classifier: Programming Language :: Python :: 3
Classifier: Programming Language :: Python :: 3.8
Classifier: Programming Language :: Python :: 3.9
Classifier: Programming Language :: Python :: 3.10
Classifier: Programming Language :: Python :: 3.11
Requires-Dist: boto3 (>=1.28.15,<2.0.0)
Requires-Dist: botocore (>=1.31.15,<2.0.0)
Requires-Dist: prometheus-api-client (>=0.4.2,<0.5.0)
Requires-Dist: pydantic (>=1.8.1,<2.0.0)
